cie_utils/__init__.py
cie_utils-0.2.0.dist-info/licenses/LICENSE
cie_utils-0.2.0.dist-info/METADATA
cie_utils-0.2.0.dist-info/WHEEL
cie_utils-0.2.0.dist-info/RECORD
