Metadata-Version: 2.4
Name: cie-utils
Version: 0.2.0
Summary: Image processing based on CIELAB color space.
License: MIT
License-File: LICENSE
Keywords: image-processing,cielab,color-space,computer-vision
Author: Jesus Alberto Rodriguez Henao
Author-email: jarh1992@gmail.com
Requires-Python: >=3.11,<4.0
Classifier: Development Status :: 3 - Alpha
Classifier: Intended Audience :: Science/Research
Classifier: License :: OSI Approved :: MIT License
Classifier: Programming Language :: Python :: 3
Classifier: Programming Language :: Python :: 3.11
Classifier: Programming Language :: Python :: 3.12
Classifier: Programming Language :: Python :: 3.13
Classifier: Programming Language :: Python :: 3.14
Classifier: Topic :: Scientific/Engineering :: Image Processing
Requires-Dist: matplotlib (>=3.10.0,<4.0.0)
Requires-Dist: numpy (>=2.2.0,<3.0.0)
Requires-Dist: opencv-python (>=4.12.0,<5.0.0)
Requires-Dist: pandas (>=2.3.0,<3.0.0)
Requires-Dist: pytz (>=2025.2,<2026.0)
Requires-Dist: pyyaml (>=6.0.0,<7.0.0)
Requires-Dist: scikit-image (>=0.25.0,<0.26.0)
Requires-Dist: scikit-learn (>=1.7.0,<2.0.0)
Requires-Dist: scipy (>=1.16.0,<2.0.0)
Project-URL: Documentation, https://jarh1992.github.io/cie-utils/
Project-URL: Homepage, https://github.com/jarh1992/cie-utils
Project-URL: Repository, https://github.com/jarh1992/cie-utils
